README.rst
tools/__init__.py
tools/cov.py
typ/__init__.py
typ/__main__.py
typ/arg_parser.py
typ/host.py
typ/json_results.py
typ/pool.py
typ/printer.py
typ/runner.py
typ/stats.py
typ/test_case.py
typ/version.py
typ/fakes/__init__.py
typ/fakes/host_fake.py
typ/fakes/test_result_server_fake.py
typ/fakes/tests/__init__.py
typ/fakes/tests/host_fake_test.py
typ/fakes/tests/test_result_server_fake_test.py
typ/tests/__init__.py
typ/tests/arg_parser_test.py
typ/tests/host_test.py
typ/tests/json_results_test.py
typ/tests/main_test.py
typ/tests/pool_test.py
typ/tests/printer_test.py
typ/tests/runner_test.py
typ/tests/stats_test.py
typ/tests/test_case_test.py
typ-0.11.0.dist-info/DESCRIPTION.rst
typ-0.11.0.dist-info/METADATA
typ-0.11.0.dist-info/RECORD
typ-0.11.0.dist-info/WHEEL
typ-0.11.0.dist-info/entry_points.txt
typ-0.11.0.dist-info/metadata.json
typ-0.11.0.dist-info/top_level.txt
