Metadata-Version: 1.1
Name: typ
Version: 0.11.0
Summary: UNKNOWN
Home-page: https://github.com/dpranke/typ
Author: Dirk Pranke
Author-email: dpranke@chromium.org
License: Apache
Platform: UNKNOWN
Classifier: Development Status :: 4 - Beta
Classifier: Intended Audience :: Developers
Classifier: License :: OSI Approved :: Apache Software License
Classifier: Programming Language :: Python :: 2
Classifier: Programming Language :: Python :: 2.7
Classifier: Programming Language :: Python :: 3
Classifier: Programming Language :: Python :: 3.6
Classifier: Topic :: Software Development :: Testing
